{
  "SoapApi" : {
    "type" : "SOAP",
    "endpoint" : "https://wssvil.sky.it/wsexistbus/ws/",
    "path" : "WS_WSC_CHECKCODICEFISCALE",
    "name" : "WS_WSC_CHECKCODICEFISCALE",
    "localPath" : "esb_it\\repo\\WS_WSC_CHECKCODICEFISCALE",
    "authentication" : "Undefined",
    "apiSpecification" : {
      "apiSpecEndpoint" : "https://wssvil.sky.it/wsexistbus/ws/WS_WSC_CHECKCODICEFISCALE?WSDL",
      "xsdSchemas" : [ ]
    },
    "integrationScenario" : "DATA_MANIPULATION",
    "bufferingSupported" : false,
    "compressionSupported" : false
  }
}